pytest_line_profiler.py
pytest_line_profiler-0.2.1.dist-info/LICENSE
pytest_line_profiler-0.2.1.dist-info/METADATA
pytest_line_profiler-0.2.1.dist-info/WHEEL
pytest_line_profiler-0.2.1.dist-info/entry_points.txt
pytest_line_profiler-0.2.1.dist-info/top_level.txt
pytest_line_profiler-0.2.1.dist-info/RECORD
