Metadata-Version: 2.1
Name: pytest-line-profiler
Version: 0.2.1
Summary: Profile code executed by pytest
Home-page: https://github.com/mgaitan/pytest-line-profiler
Author: Martín Gaitán
Author-email: gaitan@gmail.com
Maintainer: Martín Gaitán
Maintainer-email: gaitan@gmail.com
License: MIT
Classifier: Development Status :: 4 - Beta
Classifier: Framework :: Pytest
Classifier: Intended Audience :: Developers
Classifier: Topic :: Software Development :: Testing
Classifier: Programming Language :: Python
Classifier: Programming Language :: Python :: 3
Classifier: Programming Language :: Python :: 3.6
Classifier: Programming Language :: Python :: 3.7
Classifier: Programming Language :: Python :: 3.8
Classifier: Programming Language :: Python :: 3.9
Classifier: Programming Language :: Python :: 3 :: Only
Classifier: Programming Language :: Python :: Implementation :: CPython
Classifier: Programming Language :: Python :: Implementation :: PyPy
Classifier: Operating System :: OS Independent
Classifier: License :: OSI Approved :: MIT License
Requires-Python: >=3.7
License-File: LICENSE
Requires-Dist: pytest >=3.5.0
Requires-Dist: line-profiler
